Metadata-Version: 2.1
Name: InvoiceGen
Version: 0.0.1
Summary: A Very Powerfull free PDF Invoice Gen
Home-page: UNKNOWN
Author: Khushal Jethava
Author-email: Khushaljethava14@outlook.com
License: MIT
Keywords: Invoice Generator
Platform: UNKNOWN
Classifier: Development Status :: 5 - Production/Stable
Classifier: Intended Audience :: Education
Classifier: Operating System :: Microsoft :: Windows :: Windows 10
Classifier: License :: OSI Approved :: MIT License
Classifier: Programming Language :: Python :: 3
